arsenal/__init__.py
arsenal/__main__.py
arsenal/app.py
arsenal/data/cheats/README.md
arsenal/data/cheats/README.rst
arsenal/data/cheats/arsenal.md
arsenal/data/cheats/Active_directory/SCShell.md
arsenal/data/cheats/Active_directory/bloodhound.md
arsenal/data/cheats/Active_directory/certipy.md
arsenal/data/cheats/Active_directory/cme.md
arsenal/data/cheats/Active_directory/coercer.md
arsenal/data/cheats/Active_directory/kerberos.md
arsenal/data/cheats/Active_directory/laps.md
arsenal/data/cheats/Active_directory/lsassy.md
arsenal/data/cheats/Active_directory/machine_account_coerce_abuse.md
arsenal/data/cheats/Active_directory/mitm6.md
arsenal/data/cheats/Active_directory/nxc.md
arsenal/data/cheats/Active_directory/powerview.md
arsenal/data/cheats/Active_directory/responder.md
arsenal/data/cheats/Active_directory/rpcclient.md
arsenal/data/cheats/Active_directory/rubeus.md
arsenal/data/cheats/Active_directory/Impacket/impacket-execute.md
arsenal/data/cheats/Active_directory/Impacket/impacket-kerberos.md
arsenal/data/cheats/Active_directory/Impacket/impacket-secrets.md
arsenal/data/cheats/Active_directory/Impacket/impacket-servertool-mitm.md
arsenal/data/cheats/Active_directory/Impacket/impacket-smb_msrpc.md
arsenal/data/cheats/Active_directory/Impacket/impacket.md
arsenal/data/cheats/Archive/7z.md
arsenal/data/cheats/Archive/binwalk.md
arsenal/data/cheats/Archive/gzip.md
arsenal/data/cheats/Archive/rar.md
arsenal/data/cheats/Archive/tar.md
arsenal/data/cheats/Archive/unblob.md
arsenal/data/cheats/Archive/zip.md
arsenal/data/cheats/BruteForce/hydra.md
arsenal/data/cheats/BruteForce/wordlist/cewl.md
arsenal/data/cheats/BruteForce/wordlist/crunch.md
arsenal/data/cheats/Cloud/aws.md
arsenal/data/cheats/Crypto/gpg.md
arsenal/data/cheats/Databases/redis.md
arsenal/data/cheats/Deserialization/ysoserial.md
arsenal/data/cheats/Deserialization/ysoserial.net.md
arsenal/data/cheats/Files/Download/bitsadmin.md
arsenal/data/cheats/Files/Download/certutil.md
arsenal_cli-1.2.7.dist-info/LICENSE
arsenal_cli-1.2.7.dist-info/METADATA
arsenal_cli-1.2.7.dist-info/WHEEL
arsenal_cli-1.2.7.dist-info/entry_points.txt
arsenal_cli-1.2.7.dist-info/top_level.txt
arsenal_cli-1.2.7.dist-info/RECORD
