Metadata-Version: 2.1
Name: arsenal-cli
Version: 1.2.7
Summary: Arsenal is just a quick inventory, reminder and launcher for pentest commands. 
Home-page: https://github.com/Orange-Cyberdefense/arsenal
Author: Guillaume Muh, mayfly
Author-email: no-reply@orange.com
License: GPL-3.0
Keywords: security,pen testing,cli,tools,tmux
Platform: UNKNOWN
Classifier: Environment :: Console
Classifier: Intended Audience :: Developers
Classifier: Intended Audience :: System Administrators
Classifier: Intended Audience :: Information Technology
Classifier: License :: OSI Approved :: GNU General Public License v3 (GPLv3)
Classifier: Programming Language :: Python
Classifier: Programming Language :: Python :: 3
Classifier: Programming Language :: Python :: 3 :: Only
Classifier: Programming Language :: Python :: 3.6
Classifier: Programming Language :: Python :: 3.7
Classifier: Programming Language :: Python :: 3.8
Classifier: Programming Language :: Python :: 3.9
Classifier: Programming Language :: Python :: 3.10
Classifier: Topic :: Security
Classifier: Topic :: System :: Systems Administration
Classifier: Topic :: Utilities
Requires-Python: >=3.6
License-File: LICENSE
Requires-Dist: libtmux
Requires-Dist: docutils
Requires-Dist: pyperclip
Requires-Dist: pyyaml
Requires-Dist: pyfzf
